pandapg/D1.py
pandapg/D11.py
pandapg/D2.py
pandapg/D3.py
pandapg/D4.py
pandapg/D5.py
pandapg/D6.py
pandapg/D7.py
pandapg/D8.py
pandapg/D9_10.py
pandapg/__init__.py
pandapg-0.1.0.dist-info/METADATA
pandapg-0.1.0.dist-info/WHEEL
pandapg-0.1.0.dist-info/top_level.txt
pandapg-0.1.0.dist-info/RECORD
