Metadata-Version: 2.4
Name: pandapg
Version: 0.1.0
Summary: A collection of common algorithms
Author: Name
Dynamic: author
Dynamic: summary
